poc_artifactory_gitlab_lib/__init__.py
poc_artifactory_gitlab_lib/lib.py
poc_artifactory_gitlab_lib-0.1.0.dist-info/WHEEL
poc_artifactory_gitlab_lib-0.1.0.dist-info/METADATA
poc_artifactory_gitlab_lib-0.1.0.dist-info/RECORD
