Metadata-Version: 2.1
Name: poc-artifactory-gitlab-lib
Version: 0.1.0
Summary: Gitlab-CI POC project.
Author: Pierre-Yves Gillier
Author-email: pierre-yves.gillier@jellysmack.com
Requires-Python: >=3.8,<4.0
Classifier: Programming Language :: Python :: 3
Classifier: Programming Language :: Python :: 3.10
Classifier: Programming Language :: Python :: 3.8
Classifier: Programming Language :: Python :: 3.9
